contextpro/__init__.py
contextpro/_exceptions.py
contextpro/_processing.py
contextpro/feature_extraction.py
contextpro/normalization.py
contextpro/statistics.py
contextpro/tokenization.py
contextpro-2.0.1.dist-info/LICENSE
contextpro-2.0.1.dist-info/WHEEL
contextpro-2.0.1.dist-info/METADATA
contextpro-2.0.1.dist-info/RECORD
