Metadata-Version: 2.1
Name: contextpro
Version: 2.0.1
Summary: Python library for concurrent text preprocessing
Home-page: https://gitlab.com/elzawie/contextpro
License: MIT
Keywords: concurrent-preprocessing,nlp
Author: Łukasz Zawieska
Author-email: zawieskal@yahoo.com
Requires-Python: >=3.6.1,<4.0.0
Classifier: Development Status :: 3 - Alpha
Classifier: License :: OSI Approved :: MIT License
Classifier: Natural Language :: English
Classifier: Operating System :: OS Independent
Classifier: Programming Language :: Python :: 3
Classifier: Programming Language :: Python :: 3.6
Classifier: Programming Language :: Python :: 3.7
Classifier: Programming Language :: Python :: 3.8
Classifier: Programming Language :: Python :: 3.9
Classifier: Topic :: Software Development :: Libraries :: Python Modules
Requires-Dist: contractions (>=0.0.48,<0.0.49)
Requires-Dist: nltk (>=3.5,<4.0)
Requires-Dist: pandas (>=1.1.5,<2.0.0)
Requires-Dist: scipy (>=1.5.4,<2.0.0)
Requires-Dist: spacy (>=3.0.5,<4.0.0)
Requires-Dist: textblob (>=0.15.3,<0.16.0)
Requires-Dist: toml (>=0.10.2,<0.11.0)
Requires-Dist: wheel (>=0.36.2,<0.37.0)
Requires-Dist: word2number (>=1.1,<2.0)
Project-URL: Repository, https://gitlab.com/elzawie/contextpro
